{
    "kapazitaet": {
        "Q": "0.001",
        "U": "5",
        "expected": "200.000μF"
    },
    "spannung": {
        "E": "1000",
        "s": "0.01",
        "expected": "10.000V"
    },
    "energie": {
        "C": "0.001",
        "U": "10",
        "expected": "50.000mJ"
    },
    "zeitkonstante": {
        "R_RC": "1000",
        "C_RC": "0.001",
        "expected": "1.000s"
    },
    "xssPayloads": [
        "<img src=x onerror=alert(1)>",
        "<svg/onload=alert(1)>",
        "<script>alert(1)</script>"
    ]
}